[
  {
    "title": "ASHLYN MUSHROOM WALLET",
    "id": 1,
    "categoryId": 1,
    "category": "WOMEN",
    "description": "Get this stylish bag by Baggit featuring chunky chain inserts on bag handle to give you a dapper look. Made from cruelty-free material and with a diagonal top opening",
    "price": 645,
    "image": "https://i.postimg.cc/XqFfnCsy/ashylyn-mushroom-wallet.webp",
    "isAvailable": true,
    "rating": 3.4,
    "reviewCount": 250,
    "brand": "Baggit",
    "warranty": 1,
    "dimensions": " H 10.16 cm | W 19.05 cm | D 1.27 cm",
    "isNewArrival": "true"
  },
  {
    "title": "DARLO MILITARY GREEN BAG",
    "id": 2,
    "categoryId": 1,

    "category": "WOMEN",
    "description": "Get this stylish bag by Baggit featuring chunky chain inserts on eh bag handle to give you a dapper look. Made from cruelty-free material and with a diagonal top opening",
    "price": 995,
    "image": "https://i.postimg.cc/vHbg4kBK/lpxe-darlo-e-ashlyn-military-green-green-l-a-2127644-m.webp",
    "isAvailable": true,
    "rating": 4.4,
    "reviewCount": 330,
    "brand": "Baggit",
    "warranty": 1,
    "dimensions": " H 13.34 cm | W 23.50 cm | D 3.81 cm",
    "isNewArrival": "true"
  },
  {
    "title": "ASHLYN BLACK WALLET",
    "id": 3,
    "categoryId": 1,

    "category": "WOMEN",
    "description": "This trendy wallet with a exotic printed interior will revive your style and help you keep your financial essentials safe and secure.",
    "price": 845,
    "image": "https://i.postimg.cc/T1FTJyxQ/ljxe-eupe-e-ashlyn-black-black-xl-a-2126855-m.webp",
    "isAvailable": true,
    "rating": 4.4,
    "reviewCount": 330,
    "brand": "Baggit",
    "warranty": 1,
    "dimensions": " H 12.70 cm | W 20.83 cm | D 1.27 cm",
    "isNewArrival": "true"
  },
  {
    "title": "JASPER RED SADDLE BAG",
    "id": 4,
    "categoryId": 1,

    "category": "WOMEN",
    "description": "Pep up your wardrobe with your fun, polka dotted sling bag that will give you the perfect retro vibes!",
    "price": 845,
    "image": "https://i.postimg.cc/D0PqWbXJ/lpxe-jasper-e-ziba-red-red-xl-a-2127209-m.webp",
    "isAvailable": true,
    "rating": 4.5,
    "reviewCount": 430,
    "brand": "Baggit",
    "warranty": 1,
    "dimensions": "H 15.24 cm | W 22.23 cm | D 5.08 cm",
    "isNewArrival": "true"
  },
  {
    "title": "LARK GREY SADDLE BAG",
    "id": 5,
    "categoryId": 1,

    "category": "WOMEN",
    "description": "This cutesy brunch perfect sling bag features think stitchl-line design in multi colour.",
    "price": 845,
    "image": "https://i.postimg.cc/d0ctfNXF/lpxe-roam-e-lark-grey-grey-1200x1200-a-2120663-m.webp",
    "isAvailable": true,
    "rating": 4.5,
    "reviewCount": 230,
    "brand": "Baggit",
    "warranty": 1,
    "dimensions": "H 15.24 cm | W 22.23 cm | D 5.08 cm",
    "isNewArrival": "true"
  },
  {
    "title": "DIEGO PLUMPPIE SADDLE BAG",
    "id": 6,
    "categoryId": 1,

    "category": "WOMEN",
    "description": "Get this stylish bag by Baggit featuring chunky chain inserts on eh bag handle to give you a dapper look.",
    "price": 955,
    "image": "https://i.postimg.cc/XJmCpkqY/2125962.webp",
    "isAvailable": true,
    "rating": 5,
    "reviewCount": 730,
    "brand": "Baggit",
    "warranty": 1,
    "dimensions": " H 10.80 cm | W 19.05 cm | D 4.45 cm",
    "isNewArrival": "true"
  },
  {
    "title": "MONDO OLIVE HAVERSACK",
    "id": 7,
    "categoryId": 1,

    "category": "WOMEN",
    "description": "Get this stylish bag by Baggit featuring chunky chain inserts on eh bag handle to give you a dapper look.",
    "price": 985,
    "image": "https://i.postimg.cc/y6pfyMgD/lpxe-mondo-e-diego-olive-green-1200x1200-a-2124648-m.webp",
    "isAvailable": true,
    "rating": 3.5,
    "reviewCount": 130,
    "brand": "Baggit",
    "warranty": 1,
    "dimensions": " H 10.80 cm | W 19.05 cm | D 4.45 cm",
    "isNewArrival": "true"
  },
  {
    "title": "DIEGO MUSHROOM DUFFEL BAG",
    "category": "WOMEN",
    "id": 8,
    "categoryId": 1,

    "description": "Get this stylish bag by Baggit featuring chunky chain inserts on eh bag handle to give you a dapper look.",
    "price": 985,
    "image": "https://i.postimg.cc/6qRxXtFp/lpxe-aperture-e-diego-mushroom-beige-1200x1200-a-2124649-m.webp",
    "isAvailable": true,
    "rating": 4.5,
    "reviewCount": 430,
    "brand": "Baggit",
    "warranty": 1,
    "dimensions": "H 16.51 cm | W 24.13 cm | D 7.62 cm",
    "isNewArrival": "true"
  },
  {
    "title": "DARLO PLUMPPIE BAG",
    "id": 9,
    "categoryId": 1,

    "category": "WOMEN",
    "description": "Give your everyday handbag a colourful hint with this structured bag by Baggit which has an easy to reach the front zipper.",
    "price": 995,
    "image": "https://i.postimg.cc/7PMymY1K/lpxe-darlo-e-diego-plumppie-red-l-a-2127643-m.webp",
    "isAvailable": true,
    "rating": 4.5,
    "reviewCount": 430,
    "brand": "Baggit",
    "warranty": 1,
    "dimensions": "H 16.51 cm | W 24.13 cm | D 7.62 cm",
    "isNewArrival": "true"
  },
  {
    "title": "MAYZE ICE BLU WALLET",
    "id": 10,
    "categoryId": 1,

    "category": "WOMEN",
    "description": "A colour block Baggit wallet comes in a bulk-free design that's packed with pockets and slots, so you'll be organized in a minute.",
    "price": 695,
    "image": "https://i.postimg.cc/13Tts5jp/1o.webp",
    "isAvailable": true,
    "rating": 4.5,
    "reviewCount": 230,
    "brand": "Baggit",
    "warranty": 1,
    "dimensions": "H 16.51 cm | W 24.13 cm | D 7.62 cm",
    "isNewArrival": "true"
  },
  {
    "title": "GEOMTR BLACK WALLET",
    "category": "MEN",
    "id": 11,
    "categoryId": 2,

    "description": "This organized yet compact vegan wallet from Baggit with geometric thread detailing on the exterior and opens to a side fold-out panel.",
    "price": 475,
    "image": "https://i.postimg.cc/RhQJX647/men1.webp",
    "isAvailable": true,
    "rating": 4.5,
    "reviewCount": 230,
    "brand": "Baggit",
    "warranty": 1,
    "dimensions": "H 10.16 cm | W 11.43 cm | D 1.27 cm",
    "isNewArrival": "true"
  },
  {
    "title": "GRACEFUL AULI BE WALLET",
    "id": 12,
    "categoryId": 2,

    "category": "MEN",
    "description": "This organized yet compact vegan wallet from Baggit with geometric thread detailing on the exterior and opens to a side fold-out panel.",
    "price": 475,
    "image": "https://i.postimg.cc/B6JjtZxt/men2.webp",
    "isAvailable": true,
    "rating": 4.5,
    "reviewCount": 330,
    "brand": "Baggit",
    "warranty": 1,
    "dimensions": "H 10.16 cm | W 11.43 cm | D 1.27 cm",
    "isNewArrival": "true"
  },
  {
    "title": "INTERSED MUD WALLET",
    "id": 13,
    "categoryId": 2,

    "category": "MEN",
    "description": "This organized yet compact vegan wallet from Baggit with geometric thread detailing on the exterior and opens to a side fold-out panel.",
    "price": 675,
    "image": "https://i.postimg.cc/jdKtCBH9/men3.webp",
    "isAvailable": true,
    "rating": 4.5,
    "reviewCount": 250,
    "brand": "Baggit",
    "warranty": 1,
    "dimensions": "H 10.16 cm | W 11.43 cm | D 1.27 cm",
    "isNewArrival": "true"
  },
  {
    "title": "HOME BLACK WALLET",
    "id": 14,
    "categoryId": 2,

    "category": "MEN",
    "description": "This organized yet compact vegan wallet from Baggit with geometric thread detailing on the exterior and opens to a side fold-out panel.",
    "price": 575,
    "image": "https://i.postimg.cc/SNX72tm6/men4.webp",
    "isAvailable": true,
    "rating": 4.5,
    "reviewCount": 270,
    "brand": "Baggit",
    "warranty": 1,
    "dimensions": "H 10.16 cm | W 11.43 cm | D 1.27 cm",
    "isNewArrival": "true"
  },
  {
    "title": "NINION COL BLACK WALLET",
    "id": 15,
    "categoryId": 2,

    "category": "MEN",
    "description": "This organized yet compact vegan wallet from Baggit with geometric thread detailing on the exterior and opens to a side fold-out panel.",
    "price": 625,
    "image": "https://i.postimg.cc/3rG23011/men5.webp",
    "isAvailable": true,
    "rating": 2.5,
    "reviewCount": 50,
    "brand": "Baggit",
    "warranty": 1,
    "dimensions": "H 10.16 cm | W 11.43 cm | D 1.27 cm",
    "isNewArrival": "true"
  },
  {
    "title": "REET COL BROWN WALLET",
    "id": 17,
    "categoryId": 2,

    "category": "MEN",
    "description": "This organized yet compact vegan wallet from Baggit with geometric thread detailing on the exterior and opens to a side fold-out panel.",
    "price": 490,
    "image": "https://i.postimg.cc/HkK3n1G1/men7.webp",
    "isAvailable": true,
    "rating": 3.5,
    "reviewCount": 320,
    "brand": "Baggit",
    "warranty": 1,
    "dimensions": "H 10.16 cm | W 11.43 cm | D 1.27 cm",
    "isNewArrival": "true"
  },
  {
    "title": "TROIKA TRIVAGO 1 GREY WALLET",
    "id": 18,
    "categoryId": 2,

    "category": "MEN",
    "description": "This organized yet compact vegan wallet from Baggit with geometric thread detailing on the exterior and opens to a side fold-out panel.",
    "price": 790,
    "image": "https://i.postimg.cc/sDW5mQqq/men8.webp",
    "isAvailable": true,
    "rating": 3.5,
    "reviewCount": 240,
    "brand": "Baggit",
    "warranty": 1,
    "dimensions": "H 10.16 cm | W 11.43 cm | D 1.27 cm",
    "isNewArrival": "true"
  },
  {
    "title": "CENTRAL TRIOX 5 TEAL WALLET",
    "id": 19,
    "categoryId": 2,

    "category": "MEN",
    "description": "This organized yet compact vegan wallet from Baggit with geometric thread detailing on the exterior and opens to a side fold-out panel.",
    "price": 990,
    "image": "https://i.postimg.cc/251c7FRv/men9.webp",
    "isAvailable": true,
    "rating": 4.8,
    "reviewCount": 1540,
    "brand": "Baggit",
    "warranty": 1,
    "dimensions": "H 10.16 cm | W 11.43 cm | D 1.27 cm",
    "isNewArrival": "true"
  },
  {
    "title": "GW TECH AULI BLUE WALLET",
    "id": 20,
    "categoryId": 2,

    "category": "MEN",
    "description": "This organized yet compact vegan wallet from Baggit with geometric thread detailing on the exterior and opens to a side fold-out panel.",
    "price": 590,
    "image": "https://i.postimg.cc/d3K3sBjK/men10.webp",
    "isAvailable": true,
    "rating": 4.8,
    "reviewCount": 140,
    "brand": "Baggit",
    "warranty": 1,
    "dimensions": "H 10.16 cm | W 11.43 cm | D 1.27 cm",
    "isNewArrival": "true"
  },
  {
    "title": "RACER BACKPACK L BROWN",
    "id": 21,
    "categoryId": 2,

    "category": "MEN",
    "description": "Backpack or a rucksack is a larger format of a hands-free bag that's usually carried on the back and is secured with sturdy shoulder straps",
    "price": 3190,
    "image": "https://i.postimg.cc/k5KDkzWy/men11.webp",
    "isAvailable": true,
    "rating": 4.6,
    "reviewCount": 640,
    "brand": "Baggit",
    "warranty": 1,
    "dimensions": "H 10.16 cm | W 11.43 cm | D 1.27 cm",
    "isNewArrival": "true"
  },
  {
    "title": "IMMUNO LAPTOP BAG",
    "id": 22,
    "categoryId": 2,

    "category": "MEN",
    "description": "The laptop bag has a special compartment that is slightly larger than the laptop.",
    "price": 3290,
    "image": "https://i.postimg.cc/k5BLGPTx/men12.webp",
    "isAvailable": true,
    "rating": 4.8,
    "reviewCount": 430,
    "brand": "Baggit",
    "warranty": 1,
    "dimensions": "H 31.24 cm | W 38.1 cm | D 8.89 cm",
    "isNewArrival": "true"
  },
  {
    "title": "G BLOGS CITY BAG S",
    "id": 23,
    "categoryId": 2,

    "category": "MEN",
    "description": "The laptop bag has a special compartment that is slightly larger than the laptop.",
    "price": 1790,
    "image": "https://i.postimg.cc/kgct4k2X/men13.webp",
    "isAvailable": true,
    "rating": 4.8,
    "reviewCount": 440,
    "brand": "Baggit",
    "warranty": 1,
    "dimensions": "H 31.24 cm | W 38.1 cm | D 8.89 cm",
    "isNewArrival": "true"
  },
  {
    "title": "TAGGED MESSENGER M GREEN",
    "id": 24,
    "categoryId": 2,

    "category": "MEN",
    "description": "Why should men's sling bags be boring? Here's a stylish sling adorned with rich, metallic zipper.",
    "price": 1370,
    "image": "https://i.postimg.cc/SRxSxNvm/men14.webp",
    "isAvailable": true,
    "rating": 4.8,
    "reviewCount": 640,
    "brand": "Baggit",
    "warranty": 1,
    "dimensions": "H 31.24 cm | W 38.1 cm | D 8.89 cm",
    "isNewArrival": "true"
  },
  {
    "title": "SOVIET Y G Z LAPTOP BAG L RUST",
    "id": 25,
    "categoryId": 2,

    "category": "MEN",
    "description": "The laptop bag has a special compartment that is slightly larger than the laptop.",
    "price": 1870,
    "image": "https://i.postimg.cc/VkYxyH2c/men15.webp",
    "isAvailable": true,
    "rating": 4.8,
    "reviewCount": 740,
    "brand": "Baggit",
    "warranty": 1,
    "dimensions": "H 31.24 cm | W 38.1 cm | D 8.89 cm",
    "isNewArrival": "true"
  },
  {
    "title": "EXIDE LAPTOP L BROWN",
    "id": 26,
    "categoryId": 2,

    "category": "MEN",
    "description": "The laptop bag has a special compartment that is slightly larger than the laptop.",
    "price": 2490,
    "image": "https://i.postimg.cc/YCPB1zyK/men16.webp",
    "isAvailable": true,
    "rating": 4.8,
    "reviewCount": 540,
    "brand": "Baggit",
    "warranty": 1,
    "dimensions": "H 31.24 cm | W 38.1 cm | D 8.89 cm",
    "isNewArrival": "true"
  },
  {
    "title": "INVADERS MESSENGER M BLUE",
    "id": 27,
    "categoryId": 2,

    "category": "MEN",
    "description": "Originally designed for express riders, postal workers or messengers on foot, the messenger bag was meant to transport mails & goods. ",
    "price": 1434,
    "image": "https://i.postimg.cc/zX1CfmJ4/men17.webp",
    "isAvailable": true,
    "rating": 4.8,
    "reviewCount": 320,
    "brand": "Baggit",
    "warranty": 1,
    "dimensions": "H 33.02 cm | W 40.64 cm | D 9.4 cm",
    "isNewArrival": "true"
  },
  {
    "title": "LATEX LAPTOP L MUD",
    "id": 28,
    "categoryId": 2,

    "category": "MEN",
    "description": "The laptop bag has a special compartment that is slightly larger than the laptop.",
    "price": 1844,
    "image": "https://i.postimg.cc/WbHsnVhH/men18.webp",
    "isAvailable": true,
    "rating": 4.8,
    "reviewCount": 140,
    "brand": "Baggit",
    "warranty": 1,
    "dimensions": "H 33.02 cm | W 40.64 cm | D 9.4 cm",
    "isNewArrival": "true"
  },
  {
    "title": "RACER BACKPACK L BLUE",
    "id": 29,
    "categoryId": 2,

    "category": "MEN",
    "description": "Originally designed for express riders, postal workers or messengers on foot, the messenger bag was meant to transport mails & goods. ",
    "price": 3190,
    "image": "https://i.postimg.cc/gjLgb3HR/men19.webp",
    "isAvailable": true,
    "rating": 4.8,
    "reviewCount": 240,
    "brand": "Baggit",
    "warranty": 1,
    "dimensions": "H 33.02 cm | W 40.64 cm | D 9.4 cm",
    "isNewArrival": "true"
  },
  {
    "title": "CONCERT CITY BAG S BLUE",
    "id": 30,
    "categoryId": 2,

    "category": "MEN",
    "description": "Originally designed for express riders, postal workers or messengers on foot, the messenger bag was meant to transport mails & goods. ",
    "price": 1074,
    "image": "https://i.postimg.cc/ryYphxHj/men20.webp",
    "isAvailable": true,
    "rating": 4.8,
    "reviewCount": 240,
    "brand": "Baggit",
    "warranty": 1,
    "dimensions": "H 30.48 cm | W 27.94 cm | D 5.08 cm",
    "isNewArrival": "true"
  },
  {
    "title": "MOLDY CARROT SATCHEL BAG",
    "id": 31,
    "categoryId": 1,

    "category": "WOMEN",
    "description": "Get this stylish bag by Baggit featuring chunky chain inserts on eh bag handle to give you a dapper look. Made from cruelty-free material and with a diagonal top opening",
    "price": 1024,
    "image": "https://i.postimg.cc/XJYC53ZY/w1.webp",
    "isAvailable": true,
    "rating": 4.4,
    "reviewCount": 330,
    "brand": "Baggit",
    "warranty": 1,
    "dimensions": "H 27.31 cm | W 33.02 cm | D 11.43 cm",
    "isNewArrival": "true"
  },
  {
    "title": "KISHTI TOTE M2 OCHRE",
    "id": 32,
    "categoryId": 1,

    "category": "WOMEN",
    "description": "Get this stylish bag by Baggit featuring chunky chain inserts on eh bag handle to give you a dapper look. Made from cruelty-free material and with a diagonal top opening",
    "price": 1634,
    "image": "https://i.postimg.cc/02PbKPLR/w2.webp",
    "isAvailable": true,
    "rating": 4.4,
    "reviewCount": 730,
    "brand": "Baggit",
    "warranty": 1,
    "dimensions": "H 27.31 cm | W 33.02 cm | D 11.43 cm",
    "isNewArrival": "true"
  },
  {
    "title": "ZETA BOWLING",
    "id": 33,
    "categoryId": 1,

    "category": "WOMEN",
    "description": "Get this stylish bag by Baggit featuring chunky chain inserts on eh bag handle to give you a dapper look. Made from cruelty-free material and with a diagonal top opening",
    "price": 2154,
    "image": "https://i.postimg.cc/C1hQfZHn/w3.webp",
    "isAvailable": true,
    "rating": 4.4,
    "reviewCount": 230,
    "brand": "Baggit",
    "warranty": 1,
    "dimensions": "H 27.31 cm | W 33.02 cm | D 11.43 cm",
    "isNewArrival": "true"
  },
  {
    "title": "SOTTY BOWLING",
    "id": 34,
    "categoryId": 1,

    "category": "WOMEN",
    "description": "Get this stylish bag by Baggit featuring chunky chain inserts on eh bag handle to give you a dapper look. Made from cruelty-free material and with a diagonal top opening",
    "price": 1854,
    "image": "https://i.postimg.cc/xjb4NSLR/w4.jpg",
    "isAvailable": true,
    "rating": 4.4,
    "reviewCount": 230,
    "brand": "Baggit",
    "warranty": 1,
    "dimensions": "H 30.48 cm | W 36.83 cm | D 11.43 cm",
    "isNewArrival": "true"
  },
  {
    "title": "SHAUNA BOWLING",
    "id": 35,
    "categoryId": 1,

    "category": "WOMEN",
    "description": "Get this stylish bag by Baggit featuring chunky chain inserts on eh bag handle to give you a dapper look. Made from cruelty-free material and with a diagonal top opening",
    "price": 3039,
    "image": "https://i.postimg.cc/L87P1Gtt/w5.webp",
    "isAvailable": true,
    "rating": 4.4,
    "reviewCount": 230,
    "brand": "Baggit",
    "warranty": 1,
    "dimensions": "H 30.48 cm | W 36.83 cm | D 11.43 cm",
    "isNewArrival": "true"
  },
  {
    "title": "PHONICS TOTE L2 CLAY",
    "id": 36,
    "categoryId": 1,

    "category": "WOMEN",
    "description": "A bag that carries your world! A tote bag is a shoulder bag with parallel handles and comes either with or without side panels.",
    "price": 2290,
    "image": "https://i.postimg.cc/pVD31Hyd/w6.webp",
    "isAvailable": true,
    "rating": 4.4,
    "reviewCount": 230,
    "brand": "Baggit",
    "warranty": 1,
    "dimensions": "H 30.48 cm | W 36.83 cm | D 11.43 cm",
    "isNewArrival": "true"
  },
  {
    "title": "ZOE LK MP DUFFEL XS NUDE MAUVE",
    "id": 37,
    "categoryId": 1,

    "category": "WOMEN",
    "description": "Your glam outfits are calling out to this handbag from Baggit! Change up your looks by holding it as a sling or as a handcarry. ",
    "price": 1890,
    "image": "https://i.postimg.cc/L519G0Yp/w7.webp",
    "isAvailable": true,
    "rating": 4.9,
    "reviewCount": 430,
    "brand": "Baggit",
    "warranty": 1,
    "dimensions": "H 15.24 cm | W 23.5 cm | D 7.62 cm",
    "isNewArrival": "true"
  },
  {
    "title": "BLICK TOTE DARK GREY",
    "id": 38,
    "categoryId": 1,

    "category": "WOMEN",
    "description": "Your glam outfits are calling out to this handbag from Baggit! Change up your looks by holding it as a sling or as a handcarry. ",
    "price": 1545,
    "image": "https://i.postimg.cc/VvWfY0RG/w8.webp",
    "isAvailable": true,
    "rating": 4.5,
    "reviewCount": 230,
    "brand": "Baggit",
    "warranty": 1,
    "dimensions": "H 15.24 cm | W 23.5 cm | D 7.62 cm",
    "isNewArrival": "true"
  },
  {
    "title": "SPARKE TOTE IVY GREEN",
    "id": 39,
    "categoryId": 1,

    "category": "WOMEN",
    "description": "Your glam outfits are calling out to this handbag from Baggit! Change up your looks by holding it as a sling or as a handcarry. ",
    "price": 2000,
    "image": "https://i.postimg.cc/LsD3Zxs2/w9.webp",
    "isAvailable": true,
    "rating": 4.5,
    "reviewCount": 430,
    "brand": "Baggit",
    "warranty": 1,
    "dimensions": "H 29.21 cm | W 29.21 cm | D 11.43 cm",
    "isNewArrival": "true"
  },
  {
    "title": "PRINCELY ROSE HOBO",
    "id": 40,
    "categoryId": 1,

    "category": "WOMEN",
    "description": "Whether it is an office trip or everyday office commute, you can totally rely on this bag from Baggit. ",
    "price": 1495,
    "image": "https://i.postimg.cc/3RDdBrT8/w10.webp",
    "isAvailable": true,
    "rating": 4.5,
    "reviewCount": 260,
    "brand": "Baggit",
    "warranty": 1,
    "dimensions": "H 29.21 cm | W 29.21 cm | D 11.43 cm",
    "isNewArrival": "true"
  },
  {
    "title": "TRIGGER TEAL HOBO",
    "id": 41,
    "categoryId": 1,

    "category": "WOMEN",
    "description": "Whether it is an office trip or everyday office commute, you can totally rely on this bag from Baggit. ",
    "price": 1245,
    "image": "https://i.postimg.cc/3JLYkMsn/w11.webp",
    "isAvailable": true,
    "rating": 4.7,
    "reviewCount": 330,
    "brand": "Baggit",
    "warranty": 1,
    "dimensions": "H 34.29 cm | W 37.47 cm | D 13.34 cm",
    "isNewArrival": "true"
  },
  {
    "title": "CORK Y GWN BACKPACK",
    "id": 42,
    "categoryId": 1,

    "category": "WOMEN",
    "description": "Whether it is an office trip or everyday office commute, you can totally rely on this bag from Baggit. ",
    "price": 1200,
    "image": "https://i.postimg.cc/fWJ683pj/w12.webp",
    "isAvailable": true,
    "rating": 4.7,
    "reviewCount": 330,
    "brand": "Baggit",
    "warranty": 1,
    "dimensions": "H 19.05 cm | W 22.86 cm | D 6.35 cm",
    "isNewArrival": "true"
  },
  {
    "title": "NICOROBIN CITY BAG",
    "id": 43,
    "categoryId": 1,

    "category": "WOMEN",
    "description": "Whether it is an office trip or everyday office commute, you can totally rely on this bag from Baggit. ",
    "price": 4200,
    "image": "https://i.postimg.cc/wM2ytfzL/w13.webp",
    "isAvailable": true,
    "rating": 4.7,
    "reviewCount": 330,
    "brand": "Baggit",
    "warranty": 1,
    "dimensions": "H 19.05 cm | W 22.86 cm | D 6.35 cm",
    "isNewArrival": "true"
  },
  {
    "title": "L OLLY FEMME BLACK HOBO",
    "id": 44,
    "categoryId": 1,

    "category": "WOMEN",
    "description": "Go clubbing or walk into a party like a mystery with this crescent shape sling bag!",
    "price": 1440,
    "image": "https://i.postimg.cc/W1h8vrmX/w14.webp",
    "isAvailable": true,
    "rating": 4.3,
    "reviewCount": 230,
    "brand": "Baggit",
    "warranty": 1,
    "dimensions": "H 15.24 cm | W 36.83 cm | D 10.16 cm",
    "isNewArrival": "true"
  },
  {
    "title": "CRUZIE BLACK HOBO",
    "id": 45,
    "categoryId": 1,

    "category": "WOMEN",
    "description": "Go clubbing or walk into a party like a mystery with this crescent shape sling bag!",
    "price": 1140,
    "image": "https://i.postimg.cc/SRHsYw5X/w15.webp",
    "isAvailable": true,
    "rating": 4.3,
    "reviewCount": 230,
    "brand": "Baggit",
    "warranty": 1,
    "dimensions": "H 15.24 cm | W 36.83 cm | D 10.16 cm",
    "isNewArrival": "true"
  }
]
